pyrdlgen/__init__.py
pyrdlgen/core.py
pyrdlgen/bin/rdl-processor.exe
pyrdlgen-0.1.2.post2.dist-info/licenses/LICENSE
pyrdlgen-0.1.2.post2.dist-info/METADATA
pyrdlgen-0.1.2.post2.dist-info/WHEEL
pyrdlgen-0.1.2.post2.dist-info/top_level.txt
pyrdlgen-0.1.2.post2.dist-info/RECORD
