Metadata-Version: 2.4
Name: pyrdlgen
Version: 0.1.2.post2
Summary: Geração de relatórios RDL/RDLC em Python
Author: MobsterDev (Ryan Santos)
License: MIT
Classifier: Programming Language :: Python :: 3
Classifier: Operating System :: OS Independent
Classifier: License :: OSI Approved :: MIT License
Requires-Python: >=3.7
License-File: LICENSE
Dynamic: license-file
